Workbook

Sheet Sheet1
A1: proptype | B1: year | C1: value | D1: revenue | E1: drevenue | F1: expense | G1: dexpense | H1: noi | I1: capex | J1: caprate | K1: capspread | L1: stdevrev | M1: skewrev | N1: stdevexpense | O1: skewexpense | P1: stdevcapex | Q1: skewcapex | R1: stdevcapspread | S1: skewcapspread | T1: Expense Ratio | U1: IRR | V1: rev_exp_corr
A2: Full-Service Hotels | B2: 2026 | C2: 100 | D2: =H2/(1-T2) -> 36.666667 | E2: 0.0275 | F2: =D2*T2 -> 25.666667 | G2: =MIN(E2,3%) -> 0.0275 | H2: =J2*C2 -> 11 | I2: 0.3841844 | J2: 0.11 | K2: 0.005 | L2: 0.11 | M2: 0 | N2: 0.1 | O2: 0 | P2: 0.1920922 | Q2: 0 | R2: 0.02036035 | S2: -10 | T2: 0.7 | U2: 0.099375 | V2: 0.85
A3: Limited-Service Hotels | B3: 2026 | C3: 100 | D3: =H3/(1-T3) -> 17.4 | E3: 0.0275 | F3: =D3*T3 -> 8.7 | G3: =MIN(E3,3%) -> 0.0275 | H3: =J3*C3 -> 8.7 | I3: 0.25612294 | J3: 0.087 | K3: 0.005 | L3: 0.11 | M3: 0 | N3: 0.1 | O3: 0 | P3: 0.12806147 | Q3: 0 | R3: 0.018324315 | S3: 0 | T3: 0.5 | U3: 0.09296875 | V3: 0.75
A4: Seniors Housing (IL) | B4: 2026 | C4: 100 | D4: =H4/(1-T4) -> 11.7 | E4: 0.04 | F4: =D4*T4 -> 5.85 | G4: =MIN(E4,3%) -> 0.03 | H4: =J4*C4 -> 5.85 | I4: 0.23006214 | J4: 0.0585 | K4: 0.003 | L4: 0.08 | M4: 50 | N4: 0.08 | O4: 0 | P4: 0.11503107 | Q4: 0 | R4: 0.0075678145 | S4: 0 | T4: 0.5 | U4: 0.083026316 | V4: 0.6
A5: Retail- Mall | B5: 2026 | C5: 100 | D5: =H5/(1-T5) -> 13.692308 | E5: 0.025 | F5: =D5*T5 -> 4.7923077 | G5: =MIN(E5,3%) -> 0.025 | H5: =J5*C5 -> 8.9 | I5: 0.17444883 | J5: 0.089 | K5: 0.003 | L5: 0.074401329 | M5: 30 | N5: 0.11637154 | O5: 0 | P5: 0.087224415 | Q5: 0 | R5: 0.013222718 | S5: 0 | T5: 0.35 | U5: 0.10181818 | V5: 0.35
A6: Retail- Strip/Neighborhood | B6: 2026 | C6: 100 | D6: =H6/(1-T6) -> 10.153846 | E6: 0.0275 | F6: =D6*T6 -> 3.5538462 | G6: =MIN(E6,3%) -> 0.0275 | H6: =J6*C6 -> 6.6 | I6: 0.21904727 | J6: 0.066 | K6: 0.003 | L6: 0.079412472 | M6: 0 | N6: 0.11681993 | O6: 0 | P6: 0.10952364 | Q6: 0 | R6: 0.014235569 | S6: 0 | T6: 0.35 | U6: 0.079166667 | V6: 0.7
A7: Data Centers | B7: 2026 | C7: 100 | D7: =H7/(1-T7) -> 8 | E7: 0.04 | F7: =D7*T7 -> 3.2 | G7: =MIN(E7,3%) -> 0.03 | H7: =J7*C7 -> 4.8 | I7: 0.20945045 | J7: 0.048 | K7: 0.003 | L7: 0.08 | M7: 0 | N7: 0.08 | O7: 0 | P7: 0.10472523 | Q7: 0 | R7: 0.0138427 | S7: 10 | T7: 0.4 | U7: 0.0725 | V7: 0.75
A8: Self Storage | B8: 2026 | C8: 100 | D8: =H8/(1-T8) -> 8.0714286 | E8: 0.03 | F8: =D8*T8 -> 2.4214286 | G8: =MIN(E8,3%) -> 0.03 | H8: =J8*C8 -> 5.65 | I8: 0.076919094 | J8: 0.0565 | K8: 0.003 | L8: 0.088811954 | M8: 20 | N8: 0.087257114 | O8: 0 | P8: 0.038459547 | Q8: 0 | R8: 0.010788413 | S8: 0 | T8: 0.3 | U8: 0.07921875 | V8: 0.3
A9: Medical Office | B9: 2026 | C9: 100 | D9: =H9/(1-T9) -> 13.454545 | E9: 0.0325 | F9: =D9*T9 -> 6.0545455 | G9: =MIN(E9,3%) -> 0.03 | H9: =J9*C9 -> 7.4 | I9: 0.17499193 | J9: 0.074 | K9: 0.003 | L9: 0.071765779 | M9: 30 | N9: 0.068554096 | O9: 0 | P9: 0.087495966 | Q9: 0 | R9: 0.006015299 | S9: 0 | T9: 0.45 | U9: 0.092142857 | V9: 0.6
A10: Life Science | B10: 2026 | C10: 100 | D10: =H10/(1-T10) -> 14.909091 | E10: 0.0215 | F10: =D10*T10 -> 6.7090909 | G10: =MIN(E10,3%) -> 0.0215 | H10: =J10*C10 -> 8.2 | I10: 0.25025984 | J10: 0.082 | K10: 0 | L10: 0.10525648 | M10: 0 | N10: 0.10054601 | O10: 0 | P10: 0.12512992 | Q10: 0 | R10: 0.015824208 | S10: 0 | T10: 0.45 | U10: 0.089253091 | V10: 0.7
A11: Manufactured Housing | B11: 2026 | C11: 100 | D11: =H11/(1-T11) -> 7.7333333 | E11: 0.031 | F11: =D11*T11 -> 1.9333333 | G11: =MIN(E11,3%) -> 0.03 | H11: =J11*C11 -> 5.8 | I11: 0.16624085 | J11: 0.058 | K11: 0.002 | L11: 0.047061475 | M11: 0 | N11: 0.10511998 | O11: 0 | P11: 0.083120424 | Q11: 0 | R11: 0.0090793218 | S11: 0 | T11: 0.25 | U11: 0.07734375 | V11: 0.3
A12: Office (Excludes Life Science/Medical) | B12: 2026 | C12: 100 | D12: =H12/(1-T12) -> 23.7 | E12: 0.0325 | F12: =D12*T12 -> 11.85 | G12: =MIN(E12,3%) -> 0.03 | H12: =J12*C12 -> 11.85 | I12: 0.44113906 | J12: 0.1185 | K12: 0 | L12: 0.095687705 | M12: 50 | N12: 0.091405461 | O12: 0 | P12: 0.22056953 | Q12: 0 | R12: 0.015076947 | S12: 0 | T12: 0.5 | U12: 0.1000641 | V12: 0.45
A13: Retail- Net Lease | B13: 2026 | C13: 100 | D13: =H13/(1-T13) -> 7.2222222 | E13: 0.02 | F13: =D13*T13 -> 0.72222222 | G13: =MIN(E13,3%) -> 0.02 | H13: =J13*C13 -> 6.5 | I13: 0.033490175 | J13: 0.065 | K13: 0.0065 | L13: 0.059559354 | M13: 0 | N13: 0.06 | O13: 0 | P13: 0.016745088 | Q13: 0 | R13: 0.01119638 | S13: 0 | T13: 0.1 | U13: 0.073571429 | V13: 0.2
... A22: Infill Warehouses | B22: 2026 | C22: 100 | D22: =H22/(1-T22) -> 7.7142857 | E22: 0.03 | F22: =D22*T22 -> 2.3142857 | G22: =MIN(E22,3%) -> 0.03 | H22: =J22*C22 -> 5.4 | I22: 0.13648401 | J22: 0.054 | K22: 0.003 | L22: 0.078951134 | M22: 0 | N22: 0.13410809 | O22: 0 | P22: 0.068242005 | Q22: 0 | R22: 0.018083178 | S22: 0 | T22: 0.3 | U22: 0.072708333 | V22: 0.65

Sheet testing
C1: Seniors Housing (IL)
A2: Full-Service Hotels
C4: Revenue Growth | D4: =VLOOKUP(C1,Sheet1!$A$2:$S$22,5,FALSE) -> 0.04
C5: Expense Growth | D5: =VLOOKUP(C1,Sheet1!$A$2:$S$22,7,FALSE) -> 0.03
C6: CapEx | D6: =VLOOKUP(C1,Sheet1!$A$2:$S$22,9,FALSE) -> 0.23006214
C7: Going-in Cap | D7: =-E16/D13 -> 0.0585
C8: Exit Cap | D8: =VLOOKUP($C$1,Sheet1!$A$2:$S$22,11,FALSE)+D7 -> 0.0615
C9: Expense Ratio | D9: =VLOOKUP(C1,Sheet1!$A$2:$S$22,6,FALSE)/VLOOKUP(C1,Sheet1!$A$2:$S$22,4,FALSE) -> 0.5
A11: Limited-Service Hotels | D11: T0 | E11: 1 | F11: =E11+1 -> 2 | G11: =F11+1 -> 3 | H11: =G11+1 -> 4 | I11: =H11+1 -> 5 | J11: =I11+1 -> 6 | K11: =J11+1 -> 7 | L11: =K11+1 -> 8 | M11: =L11+1 -> 9 | ... O11: =N11+1 -> 11
A12: Seniors Housing (IL) | E12: 2026 | F12: =E12+1 -> 2027 | G12: =F12+1 -> 2028 | H12: =G12+1 -> 2029 | I12: =H12+1 -> 2030 | J12: =I12+1 -> 2031 | K12: =J12+1 -> 2032 | L12: =K12+1 -> 2033 | M12: =L12+1 -> 2034 | ... O12: =N12+1 -> 2036
A13: Retail- Mall | C13: Purchase | D13: -100
A14: Retail- Strip/Neighborhood | C14: Revenue | E14: =VLOOKUP(C1,Sheet1!$A$2:$S$22,4,FALSE) -> 11.7 | F14: =E14*(1+VLOOKUP($C$1,Sheet1!$A$2:$S$22,5,FALSE)) -> 12.168 | G14: =F14*(1+VLOOKUP($C$1,Sheet1!$A$2:$S$22,5,FALSE)) -> 12.65472 | H14: =G14*(1+VLOOKUP($C$1,Sheet1!$A$2:$S$22,5,FALSE)) -> 13.160909 | I14: =H14*(1+VLOOKUP($C$1,Sheet1!$A$2:$S$22,5,FALSE)) -> 13.687345 | J14: =I14*(1+VLOOKUP($C$1,Sheet1!$A$2:$S$22,5,FALSE)) -> 14.234839 | K14: =J14*(1+VLOOKUP($C$1,Sheet1!$A$2:$S$22,5,FALSE)) -> 14.804233 | L14: =K14*(1+VLOOKUP($C$1,Sheet1!$A$2:$S$22,5,FALSE)) -> 15.396402 | M14: =L14*(1+VLOOKUP($C$1,Sheet1!$A$2:$S$22,5,FALSE)) -> 16.012258 | ... O14: =N14*(1+VLOOKUP($C$1,Sheet1!$A$2:$S$22,5,FALSE)) -> 17.318858
A15: Data Centers | C15: Expense | E15: =VLOOKUP(C1,Sheet1!$A$2:$S$22,6,FALSE) -> 5.85 | F15: =E15*(1+VLOOKUP($C$1,Sheet1!$A$2:$S$22,7,FALSE)) -> 6.0255 | G15: =F15*(1+VLOOKUP($C$1,Sheet1!$A$2:$S$22,7,FALSE)) -> 6.206265 | H15: =G15*(1+VLOOKUP($C$1,Sheet1!$A$2:$S$22,7,FALSE)) -> 6.392453 | I15: =H15*(1+VLOOKUP($C$1,Sheet1!$A$2:$S$22,7,FALSE)) -> 6.5842265 | J15: =I15*(1+VLOOKUP($C$1,Sheet1!$A$2:$S$22,7,FALSE)) -> 6.7817533 | K15: =J15*(1+VLOOKUP($C$1,Sheet1!$A$2:$S$22,7,FALSE)) -> 6.9852059 | L15: =K15*(1+VLOOKUP($C$1,Sheet1!$A$2:$S$22,7,FALSE)) -> 7.1947621 | M15: =L15*(1+VLOOKUP($C$1,Sheet1!$A$2:$S$22,7,FALSE)) -> 7.410605 | ... O15: =N15*(1+VLOOKUP($C$1,Sheet1!$A$2:$S$22,7,FALSE)) -> 7.8619108
A16: Self Storage | C16: NOI | E16: =E14-E15 -> 5.85 | F16: =F14-F15 -> 6.1425 | G16: =G14-G15 -> 6.448455 | H16: =H14-H15 -> 6.7684559 | I16: =I14-I15 -> 7.1031186 | J16: =J14-J15 -> 7.4530856 | K16: =K14-K15 -> 7.8190266 | L16: =L14-L15 -> 8.2016397 | ... O16: =O14-O15 -> 9.4569473
A17: Medical Office | C17: CapEx | E17: =VLOOKUP($C$1,Sheet1!$A$2:$S$22,9,FALSE)*E16 -> 1.3458635 | F17: =VLOOKUP($C$1,Sheet1!$A$2:$S$22,9,FALSE)*F16 -> 1.4131567 | G17: =VLOOKUP($C$1,Sheet1!$A$2:$S$22,9,FALSE)*G16 -> 1.4835454 | H17: =VLOOKUP($C$1,Sheet1!$A$2:$S$22,9,FALSE)*H16 -> 1.5571655 | I17: =VLOOKUP($C$1,Sheet1!$A$2:$S$22,9,FALSE)*I16 -> 1.6341587 | J17: =VLOOKUP($C$1,Sheet1!$A$2:$S$22,9,FALSE)*J16 -> 1.7146729 | K17: =VLOOKUP($C$1,Sheet1!$A$2:$S$22,9,FALSE)*K16 -> 1.798862 | L17: =VLOOKUP($C$1,Sheet1!$A$2:$S$22,9,FALSE)*L16 -> 1.8868868 | ... O17: =VLOOKUP($C$1,Sheet1!$A$2:$S$22,9,FALSE)*O16 -> 2.1756856
A18: Life Science | C18: CF | E18: =E16-E17 -> 4.5041365 | F18: =F16-F17 -> 4.7293433 | G18: =G16-G17 -> 4.9649096 | H18: =H16-H17 -> 5.2112904 | I18: =I16-I17 -> 5.4689599 | J18: =J16-J17 -> 5.7384128 | K18: =K16-K17 -> 6.0201646 | L18: =L16-L17 -> 6.3147529 | ... O18: =O16-O17 -> 7.2812617
A19: Office (Excludes Life Science/Medical) | C19: Sale | N19: =O16/D8 -> 153.7715
A20: Retail- Net Lease | C20: Total CF | D20: =D13 -> -100 | E20: =E18 -> 4.5041365 | F20: =F18 -> 4.7293433 | G20: =G18 -> 4.9649096 | H20: =H18 -> 5.2112904 | I20: =I18 -> 5.4689599 | J20: =J18 -> 5.7384128 | K20: =K18 -> 6.0201646 | L20: =L18 -> 6.3147529 | M20: =M18 -> 6.6227382 | N20: =N18+N19 -> 160.71621
A21: Retail- Grocery Anchored
A22: Single-Family Rentals | C22: IRR | D22: =IRR(D20:N20) -> 0.090018997
A23: Regional Warehouses | C23: Stated IRR | D23: =VLOOKUP(C1,Sheet1!$A$2:$U$22,21,FALSE) -> 0.083026316
A24: Cold Storage
A25: Traditional Apartment
A26: 55+ Housing
A27: Student Housing
A28: Moderate Income Housing
A29: Infill Warehouses
